apm_crewconnect/__init__.py
apm_crewconnect/apm.py
apm_crewconnect/apm_client.py
apm_crewconnect/exceptions.py
apm_crewconnect/okta_client.py
apm_crewconnect/utils.py
apm_crewconnect/interfaces/__init__.py
apm_crewconnect/interfaces/token_manager_interface.py
apm_crewconnect/models/activity.py
apm_crewconnect/models/crew_member.py
apm_crewconnect/models/delay.py
apm_crewconnect/models/duty_period.py
apm_crewconnect/models/duty_period_component.py
apm_crewconnect/models/flight.py
apm_crewconnect/models/flight_times.py
apm_crewconnect/models/freight_info.py
apm_crewconnect/models/pairing.py
apm_crewconnect/models/passenger_info.py
apm_crewconnect/models/roster.py
apm_crewconnect-0.1.22.dist-info/METADATA
apm_crewconnect-0.1.22.dist-info/WHEEL
apm_crewconnect-0.1.22.dist-info/licenses/LICENSE.md
apm_crewconnect-0.1.22.dist-info/RECORD
