Metadata-Version: 2.4
Name: apm_crewconnect
Version: 0.1.22
Summary: A package to interact with the APM CrewConnect API
Project-URL: Homepage, https://github.com/clarkewing/apm_crewconnect
Project-URL: Issues, https://github.com/clarkewing/apm_crewconnect/issues
Author-email: Hugo Clarke-Wing <hugo@clarkewing.com>
License-File: LICENSE.md
Classifier: License :: OSI Approved :: MIT License
Classifier: Operating System :: OS Independent
Classifier: Programming Language :: Python :: 3
Requires-Python: >=3.12
Requires-Dist: pyhumps>=3.8.0
Requires-Dist: requests-oauthlib>=2.0.0
Requires-Dist: requests>=2.31.0
